fugue_jupyter/__init__.py
fugue_jupyter/_constants.py
fugue_jupyter/cmd.py
fugue_jupyter/display.py
fugue_jupyter/utils.py
fugue_jupyter/labextension/build_log.json
fugue_jupyter/labextension/package.json
fugue_jupyter/labextension/schemas/fugue-jupyter/package.json.orig
fugue_jupyter/labextension/static/lib_index_js.1b56285a6b63fec28143.js
fugue_jupyter/labextension/static/lib_index_js.1b56285a6b63fec28143.js.map
fugue_jupyter/labextension/static/remoteEntry.99193cc822ff3f92fd07.js
fugue_jupyter/labextension/static/remoteEntry.99193cc822ff3f92fd07.js.map
fugue_jupyter/labextension/static/style.js
fugue_jupyter/labextension/static/style_index_js.308b73f665deca4ee2f3.js
fugue_jupyter/labextension/static/style_index_js.308b73f665deca4ee2f3.js.map
fugue_jupyter/labextension/static/vendors-node_modules_css-loader_dist_runtime_api_js-node_modules_css-loader_dist_runtime_cssW-72eba1.c07606ee12302cc69c16.js
fugue_jupyter/labextension/static/vendors-node_modules_css-loader_dist_runtime_api_js-node_modules_css-loader_dist_runtime_cssW-72eba1.c07606ee12302cc69c16.js.map
fugue_jupyter/nbextension/README.md
fugue_jupyter/nbextension/__init__.py
fugue_jupyter/nbextension/description.yaml
fugue_jupyter/nbextension/main.js
fugue_jupyter-0.2.3.data/data/share/jupyter/labextensions/fugue-jupyter/build_log.json
fugue_jupyter-0.2.3.data/data/share/jupyter/labextensions/fugue-jupyter/install.json
fugue_jupyter-0.2.3.data/data/share/jupyter/labextensions/fugue-jupyter/package.json
fugue_jupyter-0.2.3.data/data/share/jupyter/labextensions/fugue-jupyter/schemas/fugue-jupyter/package.json.orig
fugue_jupyter-0.2.3.data/data/share/jupyter/labextensions/fugue-jupyter/static/lib_index_js.1b56285a6b63fec28143.js
fugue_jupyter-0.2.3.data/data/share/jupyter/labextensions/fugue-jupyter/static/lib_index_js.1b56285a6b63fec28143.js.map
fugue_jupyter-0.2.3.data/data/share/jupyter/labextensions/fugue-jupyter/static/remoteEntry.99193cc822ff3f92fd07.js
fugue_jupyter-0.2.3.dist-info/LICENSE
fugue_jupyter-0.2.3.dist-info/METADATA
fugue_jupyter-0.2.3.dist-info/WHEEL
fugue_jupyter-0.2.3.dist-info/entry_points.txt
fugue_jupyter-0.2.3.dist-info/top_level.txt
fugue_jupyter-0.2.3.dist-info/RECORD
