Metadata-Version: 2.1
Name: fugue-jupyter
Version: 0.2.3
Summary: Jupyterlab Extension for Fugue
Home-page: https://github.com/fugue-project/fugue-jupyter
Author: The Fugue Development Team
Author-email: hello@fugue.ai
License: BSD-3-Clause
Keywords: Jupyter,JupyterLab,JupyterLab3
Platform: Linux
Platform: Mac OS X
Platform: Windows
Classifier: License :: OSI Approved :: BSD License
Classifier: Programming Language :: Python
Classifier: Programming Language :: Python :: 3
Classifier: Programming Language :: Python :: 3.7
Classifier: Programming Language :: Python :: 3.8
Classifier: Programming Language :: Python :: 3.9
Classifier: Programming Language :: Python :: 3.10
Classifier: Framework :: Jupyter
Classifier: Framework :: Jupyter :: JupyterLab
Classifier: Framework :: Jupyter :: JupyterLab :: 3
Classifier: Framework :: Jupyter :: JupyterLab :: Extensions
Classifier: Framework :: Jupyter :: JupyterLab :: Extensions :: Prebuilt
Requires-Python: >=3.7
License-File: LICENSE
Requires-Dist: fugue (>=0.8.0)
Requires-Dist: notebook
Requires-Dist: jupyterlab (>=3.0)
Requires-Dist: jupyterlab-lsp (<4)
Requires-Dist: ipython (>=7.10.0)
